distribute_setup.py
setup.py
pygraph/__init__.py
pygraph/readwrite/__init__.py
pygraph/readwrite/dot.py
python_graph_dot.egg-info/PKG-INFO
python_graph_dot.egg-info/SOURCES.txt
python_graph_dot.egg-info/dependency_links.txt
python_graph_dot.egg-info/namespace_packages.txt
python_graph_dot.egg-info/requires.txt
python_graph_dot.egg-info/top_level.txt