Metadata-Version: 1.1
Name: python-graph-dot
Version: 1.8.2
Summary: DOT support for python-graph
Home-page: http://code.google.com/p/python-graph/
Author: Pedro Matiello
Author-email: pmatiello@gmail.com
License: MIT
Keywords: python graphs hypergraphs networks library algorithms
Platform: UNKNOWN
Classifier: License :: OSI Approved :: MIT License
Classifier: Topic :: Software Development :: Libraries :: Python Modules
